ppcd/__init__.py
ppcd/core/__init__.py
ppcd/core/eval.py
ppcd/core/infer.py
ppcd/core/train.py
ppcd/datasets/__init__.py
ppcd/datasets/datasets.py
ppcd/losses/__init__.py
ppcd/losses/losses.py
ppcd/metrics/__init__.py
ppcd/metrics/metrics.py
ppcd/models/__init__.py
ppcd/models/cdminet.py
ppcd/models/dsifn.py
ppcd/models/dtcdscd.py
ppcd/models/fast_scnn.py
ppcd/models/snunet_cd.py
ppcd/models/stanet.py
ppcd/models/unet.py
ppcd/models/backbone/__init__.py
ppcd/models/backbone/resnet.py
ppcd/models/backbone/unet.py
ppcd/models/backbone/utils.py
ppcd/models/layers/__init__.py
ppcd/models/layers/attention.py
ppcd/models/layers/initialize.py
ppcd/models/layers/layer_libs.py
ppcd/models/layers/pyramid_pool.py
ppcd/tools/__init__.py
ppcd/tools/geo_process.py
ppcd/tools/splicing.py
ppcd/tools/tailor_base.py
ppcd/traditions/__init__.py
ppcd/traditions/basics.py
ppcd/traditions/cva.py
ppcd/traditions/mrf.py
ppcd/transforms/__init__.py
ppcd/transforms/enhance.py
ppcd/transforms/functional.py
ppcd/transforms/transforms.py
ppcd/utils/__init__.py
ppcd/utils/loss_compute.py
ppcd/utils/timer.py
ppcd/utils/vis.py
ppcd-0.2.1.dist-info/LICENSE
ppcd-0.2.1.dist-info/METADATA
ppcd-0.2.1.dist-info/WHEEL
ppcd-0.2.1.dist-info/top_level.txt
ppcd-0.2.1.dist-info/RECORD
