Metadata-Version: 2.1
Name: ppcd
Version: 0.2.1
Summary: SDK about pdrscd
Home-page: https://github.com/geoyee/PdRSCD
Author: geoyee
Author-email: geoyee@yeah.net
License: UNKNOWN
Platform: UNKNOWN
Classifier: Programming Language :: Python :: 3.7
Classifier: License :: OSI Approved :: Apache Software License
Classifier: Operating System :: OS Independent
Requires-Dist: pre-commit
Requires-Dist: yapf (==0.26.0)
Requires-Dist: flake8
Requires-Dist: pyyaml (>=5.1)
Requires-Dist: visualdl (>=2.0.0)
Requires-Dist: opencv-python
Requires-Dist: tqdm
Requires-Dist: filelock
Requires-Dist: scipy
Requires-Dist: prettytable
